{
 "actions": [],
 "allow_rename": 1,
 "creation": "2024-04-29 23:24:07.698622",
 "custom": 1,
 "doctype": "DocType",
 "editable_grid": 1,
 "engine": "InnoDB",
 "field_order": [
  "car_stock_request",
  "customer_name",
  "model",
  "chassis",
  "engine_number",
  "year",
  "amount",
  "colour"
 ],
 "fields": [
  {
   "fieldname": "car_stock_request",
   "fieldtype": "Link",
   "in_list_view": 1,
   "label": "Car Stock Request",
   "options": "Car Stock Request"
  },
  {
   "fetch_from": "car_stock_request.customer_name",
   "fieldname": "customer_name",
   "fieldtype": "Data",
   "label": "Customer Name"
  },
  {
   "fetch_from": "car_stock_request.model",
   "fieldname": "model",
   "fieldtype": "Data",
   "in_list_view": 1,
   "label": "Model"
  },
  {
   "fetch_from": "car_stock_request.chassis_no",
   "fieldname": "chassis",
   "fieldtype": "Data",
   "in_list_view": 1,
   "label": "Chassis"
  },
  {
   "fetch_from": "car_stock_request.engine_no",
   "fieldname": "engine_number",
   "fieldtype": "Data",
   "in_list_view": 1,
   "label": "Engine"
  },
  {
   "columns": 1,
   "fieldname": "year",
   "fieldtype": "Data",
   "in_list_view": 1,
   "label": "Year"
  },
  {
   "columns": 1,
   "fieldname": "amount",
   "fieldtype": "Currency",
   "in_list_view": 1,
   "label": "Amount"
  },
  {
   "fieldname": "colour",
   "fieldtype": "Data",
   "label": "Colour"
  }
 ],
 "grid_page_length": 50,
 "index_web_pages_for_search": 1,
 "istable": 1,
 "links": [],
 "modified": "2025-08-25 13:14:06.048004",
 "modified_by": "alif.jefrey@mydotconsulting.com",
 "module": "DMS Sales",
 "name": "Floor Stock Facility MBB Table",
 "owner": "amirul.zulkefli@mydotconsulting.com",
 "permissions": [],
 "sort_field": "modified",
 "sort_order": "DESC",
 "states": []
}